trumbowyg/__init__.py
trumbowyg/forms.py
trumbowyg/models.py
trumbowyg/settings.py
trumbowyg/urls.py
trumbowyg/utils.py
trumbowyg/views.py
trumbowyg/widgets.py
trumbowyg/__pycache__/__init__.cpython-38.pyc
trumbowyg/__pycache__/forms.cpython-38.pyc
trumbowyg/__pycache__/models.cpython-38.pyc
trumbowyg/__pycache__/settings.cpython-38.pyc
trumbowyg/__pycache__/urls.cpython-38.pyc
trumbowyg/__pycache__/utils.cpython-38.pyc
trumbowyg/__pycache__/views.cpython-38.pyc
trumbowyg/__pycache__/widgets.cpython-38.pyc
trumbowyg/static/trumbowyg/admin.css
trumbowyg/static/trumbowyg/trumbowyg.js
trumbowyg/static/trumbowyg/trumbowyg.min.js
trumbowyg/static/trumbowyg/langs/ar.js
trumbowyg/static/trumbowyg/langs/ar.min.js
trumbowyg/static/trumbowyg/langs/bg.js
trumbowyg/static/trumbowyg/langs/bg.min.js
trumbowyg/static/trumbowyg/langs/by.js
trumbowyg/static/trumbowyg/langs/by.min.js
trumbowyg/static/trumbowyg/langs/ca.js
trumbowyg/static/trumbowyg/langs/ca.min.js
trumbowyg/static/trumbowyg/langs/cs.js
trumbowyg/static/trumbowyg/langs/cs.min.js
trumbowyg/static/trumbowyg/langs/da.js
trumbowyg/static/trumbowyg/langs/da.min.js
trumbowyg/static/trumbowyg/langs/de.js
trumbowyg/static/trumbowyg/langs/de.min.js
trumbowyg/static/trumbowyg/langs/el.js
trumbowyg/static/trumbowyg/langs/el.min.js
trumbowyg/static/trumbowyg/langs/eo.min.js
trumbowyg/static/trumbowyg/langs/es.js
trumbowyg/static/trumbowyg/langs/es.min.js
trumbowyg/static/trumbowyg/langs/es_ar.js
trumbowyg/static/trumbowyg/langs/es_ar.min.js
trumbowyg/static/trumbowyg/langs/fa.js
trumbowyg/static/trumbowyg/langs/fa.min.js
trumbowyg/static/trumbowyg/langs/fi.js
trumbowyg/static/trumbowyg/langs/fi.min.js
trumbowyg/static/trumbowyg/langs/fr.js
trumbowyg/static/trumbowyg/langs/fr.min.js
trumbowyg/static/trumbowyg/langs/he.js
trumbowyg/static/trumbowyg/langs/he.min.js
trumbowyg/static/trumbowyg/langs/hr.js
trumbowyg/static/trumbowyg/langs/hr.min.js
trumbowyg/static/trumbowyg/langs/hu.js
trumbowyg/static/trumbowyg/langs/hu.min.js
django_trumbowyg-1.1.2.dist-info/LICENSE.txt
django_trumbowyg-1.1.2.dist-info/METADATA
django_trumbowyg-1.1.2.dist-info/WHEEL
django_trumbowyg-1.1.2.dist-info/top_level.txt
django_trumbowyg-1.1.2.dist-info/RECORD
