Metadata-Version: 2.1
Name: django-trumbowyg
Version: 1.1.2
Summary: Trumbowyg (WYSIWYG editor) integration app for Django admin.
Home-page: https://github.com/sandino/django-trumbowyg
Author: sandino
Author-email: vdjangofan@gmail.com
License: The MIT License (MIT)
Platform: UNKNOWN
Classifier: Development Status :: 5 - Production/Stable
Classifier: Environment :: Web Environment
Classifier: Intended Audience :: Developers
Classifier: Operating System :: OS Independent
Classifier: Programming Language :: Python
Classifier: Framework :: Django
Requires-Dist: six
